tests/__init__.py
tests/dependencies/__init__.py
tests/dependencies/conftest.py
tests/dependencies/dep.py
tests/unit/__init__.py
tests/unit/conftest.py
tests/unit/functions.py
tests/unit/test_dask.py
tests/unit/test_excel.py
tests/unit/test_hdf5.py
tests/unit/test_joblib.py
tests/unit/test_json.py
tests/unit/test_pandas.py
tests/unit/test_parquet.py
tests/unit/vanilla/__init__.py
tests/unit/vanilla/test_fs_initialisation.py
tests/unit/vanilla/test_io.py
tests/unit/vanilla/test_multiproject.py
tests/unit/vanilla/test_path_creation.py
tests/unit/vanilla/test_vanilla.py
tests/unit/vanilla/test_zipfile.py
transparentpath/__init__.py
transparentpath/_version.py
transparentpath/gcsutils/__init__.py
transparentpath/gcsutils/methodtranslator.py
transparentpath/gcsutils/transparentpath.py
transparentpath/io/__init__.py
transparentpath/io/_dask.py
transparentpath/io/_excel.py
transparentpath/io/_hdf5.py
transparentpath/io/_io.py
transparentpath/io/_joblib_load.py
transparentpath/io/_json.py
transparentpath/io/_pandas.py
transparentpath/io/_parquet.py
transparentpath/io/_zipfile.py
transparentpath-1.1.38.dist-info/LICENSE
transparentpath-1.1.38.dist-info/METADATA
transparentpath-1.1.38.dist-info/WHEEL
transparentpath-1.1.38.dist-info/top_level.txt
transparentpath-1.1.38.dist-info/RECORD
