Metadata-Version: 2.1
Name: transparentpath
Version: 1.1.38
Summary: A class that allows one to use a path in a local file system or a gcs file system (more or less) in almost the same way one would use a pathlib.Path object.
Home-page: https://github.com/Advestis/transparentpath
Author: Advestis
Author-email: pythondev@advestis.com
License: GPLv3
Project-URL: Bug Tracker, https://github.com/Advestis/transparentpath/issues
Project-URL: Documentation, https://advestis.github.io/transparentpath
Project-URL: Source Code, https://github.com/Advestis/transparentpath/
Classifier: Development Status :: 5 - Production/Stable
Classifier: Operating System :: Unix
Classifier: Programming Language :: Python :: 3.8
Requires-Python: >=3.7
License-File: LICENSE
Requires-Dist: gcsfs (==2022.2.0)
Requires-Dist: fsspec (==2022.2.0)
Requires-Dist: setuptools
Requires-Dist: datetime
Provides-Extra: all
Requires-Dist: dask ; extra == 'all'
Requires-Dist: distributed ; extra == 'all'
Requires-Dist: pandas ; extra == 'all'
Requires-Dist: xlrd ; extra == 'all'
Requires-Dist: openpyxl ; extra == 'all'
Requires-Dist: h5py ; extra == 'all'
Requires-Dist: tables ; extra == 'all'
Requires-Dist: joblib ; extra == 'all'
Requires-Dist: numpy ; extra == 'all'
Requires-Dist: pyarrow ; extra == 'all'
Requires-Dist: fastparquet ; extra == 'all'
Provides-Extra: dask
Requires-Dist: dask ; extra == 'dask'
Requires-Dist: distributed ; extra == 'dask'
Provides-Extra: excel
Requires-Dist: pandas ; extra == 'excel'
Requires-Dist: xlrd ; extra == 'excel'
Requires-Dist: openpyxl ; extra == 'excel'
Provides-Extra: hdf5
Requires-Dist: h5py ; extra == 'hdf5'
Requires-Dist: tables ; extra == 'hdf5'
Provides-Extra: joblib
Requires-Dist: joblib ; extra == 'joblib'
Requires-Dist: numpy ; extra == 'joblib'
Provides-Extra: json
Requires-Dist: numpy ; extra == 'json'
Requires-Dist: pandas ; extra == 'json'
Provides-Extra: pandas
Requires-Dist: pandas ; extra == 'pandas'
Provides-Extra: parquet
Requires-Dist: numpy ; extra == 'parquet'
Requires-Dist: pandas ; extra == 'parquet'
Requires-Dist: pyarrow ; extra == 'parquet'
Requires-Dist: fastparquet ; extra == 'parquet'
